amarillo_stops/stops.py
amarillo_stops/stop_importer/__init__.py
amarillo_stops/stop_importer/base.py
amarillo_stops/stop_importer/gtfs.py
amarillo_stops/stop_importer/overpass.py
amarillo_stops/tests/__init__.py
amarillo_stops/tests/test_stops_gtfs_importer.py
amarillo_stops/tests/test_stops_overpass_importer.py
amarillo_stops/tests/test_stops_store.py
amarillo_stops-2.0.0.dist-info/LICENSE
amarillo_stops-2.0.0.dist-info/METADATA
amarillo_stops-2.0.0.dist-info/WHEEL
amarillo_stops-2.0.0.dist-info/top_level.txt
amarillo_stops-2.0.0.dist-info/RECORD
