Metadata-Version: 2.1
Name: amarillo-stops
Version: 2.0.0
Summary: Stops service for Amarillo
License: GNU AFFERO GENERAL PUBLIC LICENSE
License-File: LICENSE
Requires-Dist: amarillo
